<?xml version="1.0"?>
<registry>
  <record name='localtest.samplefield.behavior_mappings'>
    <field type="plone.registry.field.Text">
      <title>Behavior mappings (JSON)</title>
      <description>JSON</description>
      <default />
    </field>
    <value>{"meta":{"target_scope":"site","site_id":null},"mappings":{"Client":["localtest.samplefield.behaviors.client_detail.IClientDetail"]}}</value>
  </record>
  <record name='localtest.samplefield.extender_gates'>
    <field type="plone.registry.field.Text">
      <title>SchemaExtender site gates (JSON)</title>
      <description>JSON</description>
      <default />
    </field>
    <value>{}</value>
  </record>
  <record name='localtest.samplefield.listing_patches'>
    <field type="plone.registry.field.Text">
      <title>Listing patches (JSON)</title>
      <description>JSON</description>
      <default />
    </field>
    <value>{}</value>
  </record>
  <record name='localtest.samplefield.template_assets'>
    <field type="plone.registry.field.Text">
      <title>Template assets (JSON)</title>
      <description>JSON</description>
      <default />
    </field>
    <value>{}</value>
  </record>
</registry>
